tradernet/PublicApiClient.py
tradernet/__init__.py
tradernet/client.py
tradernet/common/__init__.py
tradernet/common/netutils.py
tradernet/common/string_utils.py
tradernet/common/ws_utils.py
tradernet/core.py
tradernet/extensions.py
tradernet/py.typed
tradernet/symbols/__init__.py
tradernet/symbols/base_market_symbol.py
tradernet/symbols/base_option_symbol.py
tradernet/symbols/das_option.py
tradernet/symbols/option_properties.py
tradernet/symbols/tradernet_option.py
tradernet/symbols/tradernet_symbol.py
tradernet/tradernet_wsapi.py
tradernet/trading.py
tradernet_sdk-1.3.0.dist-info/LICENSE
tradernet_sdk-1.3.0.dist-info/METADATA
tradernet_sdk-1.3.0.dist-info/WHEEL
tradernet_sdk-1.3.0.dist-info/RECORD
