Metadata-Version: 2.3
Name: tradernet-sdk
Version: 1.3.0
Summary: Public API for Tradernet
License: MIT
Author: Anton Kudelin
Author-email: a.kudelin@freedomfinance.eu
Requires-Python: >=3.8
Classifier: License :: OSI Approved :: MIT License
Classifier: Programming Language :: Python :: 3
Classifier: Programming Language :: Python :: 3.8
Classifier: Programming Language :: Python :: 3.9
Classifier: Programming Language :: Python :: 3.10
Classifier: Programming Language :: Python :: 3.11
Classifier: Programming Language :: Python :: 3.12
Classifier: Programming Language :: Python :: 3.13
Requires-Dist: aiohttp (>=3.8.4)
Requires-Dist: certifi (>=2023.5.7)
Requires-Dist: lxml (>=4.9.3)
Requires-Dist: mypy-extensions (>=1.0.0)
Requires-Dist: numpy (>=1.21.2)
Requires-Dist: requests (>=2.29.0)
Project-URL: Homepage, https://tradernet.ru/tradernet-api/python-sdk
